cs/upd.py
cs_upd-20250426.dist-info/WHEEL
cs_upd-20250426.dist-info/METADATA
cs_upd-20250426.dist-info/RECORD
