Metadata-Version: 2.4
Name: cs-upd
Version: 20250426
Summary: Single and multiple line status updates with minimal update sequences.
Keywords: python2,python3
Author-email: Cameron Simpson <cs@cskk.id.au>
Classifier: Programming Language :: Python
Classifier: Programming Language :: Python :: 3
Classifier: Development Status :: 4 - Beta
Classifier: Intended Audience :: Developers
Classifier: Operating System :: OS Independent
Classifier: Topic :: Software Development :: Libraries :: Python Modules
Classifier: License :: OSI Approved :: GNU General Public License v3 or later (GPLv3+)
Requires-Dist: cs.context>=20250412
Requires-Dist: cs.deco>=20250306
Requires-Dist: cs.gimmicks>=20250323
Requires-Dist: cs.lex>=20250414
Requires-Dist: cs.obj>=20210122
Requires-Dist: cs.pfx>=20250308
Requires-Dist: cs.resources>=20250325
Requires-Dist: cs.threads>=20250325
Requires-Dist: cs.tty
Requires-Dist: cs.units
Project-URL: MonoRepo Commits, https://bitbucket.org/cameron_simpson/css/commits/branch/main
Project-URL: Monorepo Git Mirror, https://github.com/cameron-simpson/css
Project-URL: Monorepo Hg/Mercurial Mirror, https://hg.sr.ht/~cameron-simpson/css
Project-URL: Source, https://github.com/cameron-simpson/css/blob/main/lib/python/cs/upd.py
